llmonitor/__init__.py
llmonitor/consumer.py
llmonitor/event_queue.py
llmonitor/langchain.py
llmonitor/openai_utils.py
llmonitor/parsers.py
llmonitor/tags.py
llmonitor/users.py
llmonitor-0.0.50.dist-info/METADATA
llmonitor-0.0.50.dist-info/WHEEL
llmonitor-0.0.50.dist-info/RECORD
