Metadata-Version: 2.1
Name: llmonitor
Version: 0.0.50
Summary: Observability and monitoring for AI apps
Home-page: https://github.com/llmonitor/llmonitor-py/
Keywords: LLMonitor,Langchain,AI,Analytics,Monitoring
Author: llmonitor
Author-email: hello@llmonitor.com
Requires-Python: >=3.8.1,<4.0.0
Classifier: Programming Language :: Python :: 3
Classifier: Programming Language :: Python :: 3.9
Classifier: Programming Language :: Python :: 3.10
Classifier: Programming Language :: Python :: 3.11
Classifier: Programming Language :: Python :: 3.12
Requires-Dist: opentelemetry-api (>=1.21.0,<2.0.0)
Requires-Dist: opentelemetry-sdk (>=1.21.0,<2.0.0)
Requires-Dist: requests (>=2.31.0,<3.0.0)
Requires-Dist: setuptools (>=68.2.2,<69.0.0)
Requires-Dist: tenacity (>=8.2.3,<9.0.0)
Project-URL: Documentation, https://llmonitor.com/docs/py/usage
Project-URL: Repository, https://github.com/llmonitor/llmonitor-py/
